[
    {
        "key": "dbln",
        "value": "%7B%2261579403792759%22%3A%22iKpvdz6l%22%7D",
        "domain": "facebook.com",
        "path": "/login/device-based/",
        "hostOnly": false,
        "creation": "2026-03-25T17:36:17.427Z",
        "lastAccessed": "2026-03-25T17:36:17.428Z"
    },
    {
        "key": "datr",
        "value": "QWe6aVYgMHw8z4lm1XUcNbDT",
        "domain": "facebook.com",
        "path": "/",
        "hostOnly": false,
        "creation": "2026-03-25T17:36:17.428Z",
        "lastAccessed": "2026-03-25T17:36:17.428Z"
    },
    {
        "key": "sb",
        "value": "DGi6aZH1zTeN-28y2lZBNRT1",
        "domain": "facebook.com",
        "path": "/",
        "hostOnly": false,
        "creation": "2026-03-25T17:36:17.428Z",
        "lastAccessed": "2026-03-25T17:36:17.428Z"
    },
    {
        "key": "pas",
        "value": "61579403792759%3AGJOcowQAfl",
        "domain": "facebook.com",
        "path": "/",
        "hostOnly": false,
        "creation": "2026-03-25T17:36:17.428Z",
        "lastAccessed": "2026-03-25T17:36:17.428Z"
    },
    {
        "key": "ps_l",
        "value": "1",
        "domain": "facebook.com",
        "path": "/",
        "hostOnly": false,
        "creation": "2026-03-25T17:36:17.428Z",
        "lastAccessed": "2026-03-25T17:36:17.428Z"
    },
    {
        "key": "ps_n",
        "value": "1",
        "domain": "facebook.com",
        "path": "/",
        "hostOnly": false,
        "creation": "2026-03-25T17:36:17.428Z",
        "lastAccessed": "2026-03-25T17:36:17.428Z"
    },
    {
        "key": "vpd",
        "value": "v1%3B618x360x2",
        "domain": "facebook.com",
        "path": "/",
        "hostOnly": false,
        "creation": "2026-03-25T17:36:17.429Z",
        "lastAccessed": "2026-03-25T17:36:17.429Z"
    },
    {
        "key": "locale",
        "value": "en_US",
        "domain": "facebook.com",
        "path": "/",
        "hostOnly": false,
        "creation": "2026-03-25T17:36:17.429Z",
        "lastAccessed": "2026-03-25T17:36:17.429Z"
    },
    {
        "key": "m_pixel_ratio",
        "value": "2",
        "domain": "facebook.com",
        "path": "/",
        "hostOnly": false,
        "creation": "2026-03-25T17:36:17.429Z",
        "lastAccessed": "2026-03-25T17:36:17.429Z"
    },
    {
        "key": "wd",
        "value": "360x806",
        "domain": "facebook.com",
        "path": "/",
        "hostOnly": false,
        "creation": "2026-03-25T17:36:17.429Z",
        "lastAccessed": "2026-03-25T17:36:17.429Z"
    },
    {
        "key": "c_user",
        "value": "61579403792759",
        "domain": "facebook.com",
        "path": "/",
        "hostOnly": false,
        "creation": "2026-03-25T17:36:17.429Z",
        "lastAccessed": "2026-03-25T17:36:17.429Z"
    },
    {
        "key": "xs",
        "value": "12%3AaQDxqzkRGhl5qg%3A2%3A1774459707%3A-1%3A-1",
        "domain": "facebook.com",
        "path": "/",
        "hostOnly": false,
        "creation": "2026-03-25T17:36:17.429Z",
        "lastAccessed": "2026-03-25T17:36:17.429Z"
    },
    {
        "key": "fr",
        "value": "0fbU87yWABLiGkVIW.AWfdDWun9GDYhPKw6FWGSTdcsTCljkuYGjc2RnMxDb9_hnHq_PY.BpumdC..AAA.0.0.BpxBs9.AWdBZZZE6kNrq2_R9hPaL23SmJ8",
        "domain": "facebook.com",
        "path": "/",
        "hostOnly": false,
        "creation": "2026-03-25T17:36:17.429Z",
        "lastAccessed": "2026-03-25T17:36:17.429Z"
    },
    {
        "key": "wl_cbv",
        "value": "v2%3Bclient_version%3A3122%3Btimestamp%3A1774459710",
        "domain": "facebook.com",
        "path": "/",
        "hostOnly": false,
        "creation": "2026-03-25T17:36:17.429Z",
        "lastAccessed": "2026-03-25T17:36:17.429Z"
    },
    {
        "key": "fbl_st",
        "value": "101739497%3BT%3A29574328",
        "domain": "facebook.com",
        "path": "/",
        "hostOnly": false,
        "creation": "2026-03-25T17:36:17.429Z",
        "lastAccessed": "2026-03-25T17:36:17.429Z"
    }
        ]
